graphamazur/__init__.py
graphamazur/algorithms.py
graphamazur/graph_basics.py
graphamazur-0.0.3.dist-info/METADATA
graphamazur-0.0.3.dist-info/WHEEL
graphamazur-0.0.3.dist-info/licenses/LICENSE
graphamazur-0.0.3.dist-info/RECORD
