Metadata-Version: 2.4
Name: graphamazur
Version: 0.0.3
Summary: Библиотека для работы с графами
Author-email: admazurkevich <mazurnastya28@gmail.com>
License-File: LICENSE
Classifier: License :: OSI Approved :: MIT License
Classifier: Operating System :: OS Independent
Classifier: Programming Language :: Python :: 3
Requires-Python: >=3.10.0
